setup.py
MawaqitAPI/__init__.py
MawaqitAPI/constants.py
MawaqitAPI/google.py
MawaqitAPI/helper.py
MawaqitAPI/localMawaqit.py
MawaqitAPI/mawaqit.py
MawaqitAPI/scraper.py
example/example.py
py_mawaqit-0.0.7.dist-info/METADATA
py_mawaqit-0.0.7.dist-info/WHEEL
py_mawaqit-0.0.7.dist-info/licenses/LICENSE.txt
py_mawaqit-0.0.7.dist-info/RECORD
