Metadata-Version: 2.1
Name: py-mawaqit
Version: 0.0.7
Summary: An unofficial Mawaqit wrapper for python. It scrapes the mawaqit website to get the prayer times for a given mosque.
Project-URL: Homepage, https://github.com/RiadZX/py-mawaqit/
Project-URL: Bug Tracker, https://github.com/RiadZX/py-mawaqit/issues
Author-email: Riad Zaid <riadzaid100@gmail.com>
License-File: LICENSE.txt
Classifier: License :: OSI Approved :: MIT License
Classifier: Operating System :: OS Independent
Classifier: Programming Language :: Python :: 3
Requires-Python: >=3.7
